setup.py
speg/__init__.py
speg/peg.py
speg.egg-info/PKG-INFO
speg.egg-info/SOURCES.txt
speg.egg-info/dependency_links.txt
speg.egg-info/top_level.txt