Metadata-Version: 1.0
Name: speg
Version: 0.2
Summary: A PEG-based parser interpreter with memoization
Home-page: https://github.com/avakar/speg
Author: Martin Vejnár
Author-email: vejnar.martin@gmail.com
License: MIT
Platform: UNKNOWN
